quartet_templates/__init__.py
quartet_templates/admin.py
quartet_templates/apps.py
quartet_templates/models.py
quartet_templates/routers.py
quartet_templates/serializers.py
quartet_templates/steps.py
quartet_templates/urls.py
quartet_templates/views.py
quartet_templates/migrations/0001_initial.py
quartet_templates/migrations/0002_auto_20190305_2241.py
quartet_templates/migrations/0003_alter_template_id.py
quartet_templates/migrations/__init__.py
tests/__init__.py
tests/settings.py
tests/test_templates.py
tests/tests.py
tests/urls.py
quartet_templates-3.0.1.dist-info/LICENSE
quartet_templates-3.0.1.dist-info/METADATA
quartet_templates-3.0.1.dist-info/WHEEL
quartet_templates-3.0.1.dist-info/top_level.txt
quartet_templates-3.0.1.dist-info/RECORD
