Metadata-Version: 2.1
Name: quartet-templates
Version: 3.0.1
Summary: Template package for QU4RTET
Home-page: https://gitlab.com/serial-lab/quartet_templates
Author: SerialLab Corp
Author-email: slab@serial-lab.com
License: GPLv3
Keywords: seriallab,quartet level-4 quartet
Platform: UNKNOWN
Classifier: Development Status :: 5 - Production/Stable
Classifier: Environment :: Web Environment
Classifier: Framework :: Django
Classifier: Intended Audience :: Developers
Classifier: License :: OSI Approved :: GNU General Public License v3 (GPLv3)
Classifier: Natural Language :: English
Classifier: Programming Language :: Python :: 3.5
Classifier: Programming Language :: Python :: 3.6
